{
  "rightTeamName": "المهندسين",
  "leftTeamName": "الاطباء",
  "parts": [
    [
      {
        "text": "ما هي أسباب تحديد الأشخاص الذين يحتاجون إلى تحديد أشخاص أخرين؟",
        "answer": "السلام عليكم ورحمة الله و بركاته السلام عليكم ورحمة الله و بركاته السلام عليكم ورحمة الله و بركاته السلام عليكم ورحمة الله و بركاتهالسلام عليكم ورحمة الله و بركاته",
        "duration": 30,
        "marks": 0
      },
      {
        "text": "قيمة 5+3",
        "answer": "السلام عليكم ورحمة الله و بركاته",
        "duration": 10,
        "marks": 0
      }
    ],
    [
      {
        "name": "العلوم الطبيعية",
        "questions": [
          {
            "text": "ما هي أسباب تحديد الأشخاص الذين يحتاجون إلى تحديد أشخاص أخرين؟",
            "answer": "السلام عليكم ورحمة الله و بركاته السلام عليكم ورحمة الله و بركاته السلام عليكم ورحمة الله و بركاته السلام عليكم ورحمة الله و بركاتهالسلام عليكم ورحمة الله و بركاته",
            "duration": 120,
            "marks": 8
          },
          {
            "text": "قيمة 5+3",
            "answer": "السلام عليكم ورحمة الله و بركاته",
            "duration": 120,
            "marks": 8
          }
        ]
      },
      {
        "name": "العلوم الانسانية",
        "questions": [
          {
            "text": "",
            "answer": "",
            "duration": 120,
            "marks": 8
          },
          {
            "text": "",
            "answer": "",
            "duration": 120,
            "marks": 8
          }
        ]
      },
      {
        "name": "الرياضة",
        "questions": [
          {
            "text": "",
            "answer": "",
            "duration": 120,
            "marks": 8
          },
          {
            "text": "",
            "answer": "",
            "duration": 120,
            "marks": 8
          }
        ]
      },
      {
        "name": "الأدب و الفنون",
        "questions": [
          {
            "text": "",
            "answer": "",
            "duration": 120,
            "marks": 8
          },
          {
            "text": "",
            "answer": "",
            "duration": 120,
            "marks": 8
          }
        ]
      },
      {
        "name": "الدين و السيرة",
        "questions": [
          {
            "text": "",
            "answer": "",
            "duration": 120,
            "marks": 8
          },
          {
            "text": "",
            "answer": "",
            "duration": 120,
            "marks": 8
          }
        ]
      }
    ],
    [
      {
        "text": "ما هي أسباب تحديد الأشخاص الذين يحتاجون إلى تحديد أشخاص أخرين؟",
        "answer": "السلام عليكم ورحمة الله و بركاته السلام عليكم ورحمة الله و بركاته السلام عليكم ورحمة الله و بركاته السلام عليكم ورحمة الله و بركاتهالسلام عليكم ورحمة الله و بركاته",
        "duration": 120,
        "marks": 0
      },
      {
        "text": "قيمة 5+3",
        "answer": "السلام عليكم ورحمة الله و بركاته",
        "duration": 120,
        "marks": 0
      }
    ],
    [
      [
        {
          "text": "ما هي أسباب تحديد الأشخاص الذين يحتاجون إلى تحديد أشخاص أخرين؟",
          "answer": "السلام عليكم ورحمة الله و بركاته السلام عليكم ورحمة الله و بركاته السلام عليكم ورحمة الله و بركاته السلام عليكم ورحمة الله و بركاتهالسلام عليكم ورحمة الله و بركاته",
          "duration": 30,
          "marks": 2
        },
        {
          "text": "قيمة 5+3",
          "answer": "السلام عليكم ورحمة الله و بركاته",
          "duration": 30,
          "marks": 2
        }
      ],
      [
        {
          "text": "ما هي أسباب تحديد الأشخاص الذين يحتاجون إلى تحديد أشخاص أخرين2؟",
          "answer": "السلام عليكم ورحمة الله و بركاته السلام عليكم ورحمة الله و بركاته السلام عليكم ورحمة الله و بركاته السلام عليكم ورحمة الله و بركاتهالسلام عليكم ورحمة الله و بركاته",
          "duration": 30,
          "marks": 2
        },
        {
          "text": "قيمة 5+23",
          "answer": "السلام عليكم ورحمة الله و بركاته",
          "duration": 30,
          "marks": 2
        }
      ]
    ]
  ]
}
